[
    {
        "id": "23w",
        "name": "臺灣股票資訊軟體製作",
        "closed": true,
        "date": "2022/04/27",
        "description": "",
        "event": [
            "臺灣股票資訊軟體製作"
        ]
    },
    {
        "id": "22v",
        "name": "聊天室開始製作",
        "closed": true,
        "date": "2022/04/01",
        "description": "",
        "event": [
            "聊天室開始製作"
        ]
    },
    {
        "id": "21u",
        "name": "告白牆開始製作",
        "closed": true,
        "date": "2022/02/01",
        "description": "",
        "event": [
            "告白牆開始製作"
        ]
    },
    {
        "id": "20t",
        "name": "靈萌團隊官網重建完成",
        "closed": true,
        "date": "2022/02/04",
        "description": "",
        "event": [
            "靈萌團隊官網重建完成"
        ]
    },
    {
        "id": "19s",
        "name": "頭腦個人網頁成立",
        "closed": true,
        "date": "2022/02/03",
        "description": "",
        "event": [
            "頭腦個人網頁成立"
        ]
    },
    {
        "id": "18r",
        "name": "DCbot 網頁建構完成",
        "closed": true,
        "date": "2022/02/02",
        "description": "",
        "event": [
            "CutespiritDiscordBot 網頁建構完成"
        ]
    },
    {
        "id": "17q",
        "name": "成立部落格",
        "closed": true,
        "date": "2022/02/01",
        "description": "",
        "event": [
            "夏特稀部落格成立",
            "靈萌部落格成立"
        ]
    },
    {
        "id": "16p",
        "name": "靈萌團隊雲端重建完成",
        "closed": true,
        "date": "2022/01/28",
        "description": "",
        "event": [
            "靈萌團隊雲端重建完成"
        ]
    },
    {
        "id": "15o",
        "name": "靈萌狀態頁面建構完成",
        "closed": true,
        "date": "2022/01/27",
        "description": "",
        "event": [
            "靈萌狀態頁面建構完成"
        ]
    },
    {
        "id": "14n",
        "name": "aapanel建構完成",
        "closed": true,
        "date": "2022/01/26",
        "description": "",
        "event": [
            "aapanel建構完成"
        ]
    },
    {
        "id": "13m",
        "name": "團隊雲端設立",
        "closed": true,
        "date": "2022/01/24",
        "description": "",
        "event": [
            "團隊新增VPS",
            "翼手龍面板建構完成",
            "團隊雲端建構完成",
            "5steveLan 加入團隊"
        ]
    },
    {
        "id": "12l",
        "name": "嘴人產生器開始服務",
        "closed": true,
        "date": "2022/01/22",
        "description": "",
        "event": [
            "嘴人產生器開始服務"
        ]
    },
    {
        "id": "11k",
        "name": "頭腦加入團隊",
        "closed": true,
        "date": "2022/01/18",
        "description": "",
        "event": [
            "頭腦加入團隊"
        ]
    },
    {
        "id": "10j",
        "name": "Salt加入團隊",
        "closed": true,
        "date": "2022/01/02",
        "description": "",
        "event": [
            "Salt加入團隊"
        ]
    },
    {
        "id": "9i",
        "name": "萌弟退出團隊並辭職副團長",
        "closed": true,
        "date": "2022/01/01",
        "description": "",
        "event": [
            "萌弟(CuteUSB)退出團隊",
            "萌弟(CuteUSB) 辭職副團長",
            "進行靈萌團隊重大變革討論"
        ]
    },
    {
        "id": "8h",
        "name": "靈萌團隊服務停止運作",
        "closed": true,
        "date": "2021/11/12",
        "description": "",
        "event": [
            "官網停止運作",
            "靈萌雲端停止運作",
            "靈萌搜尋引擎停止運作",
            "靈萌社交停止運作"
        ]
    },
    {
        "id": "7g",
        "name": "靈萌商店暫停營運",
        "closed": true,
        "date": "2021/11/10",
        "description": "",
        "event": [
            "靈萌商店暫停營運"
        ]
    },
    {
        "id": "6f",
        "name": "靈萌雲端成立",
        "closed": true,
        "date": "2021/08/01",
        "description": "",
        "event": [
            "靈萌雲端成立"
        ]
    },
    {
        "id": "5e",
        "name": "靈萌官網成立",
        "closed": true,
        "date": "2021/07/29",
        "description": "",
        "event": [
            "靈萌官網成立"
        ]
    },
    {
        "id": "4d",
        "name": "正式成立靈萌商店",
        "closed": true,
        "date": "2021/07/23",
        "description": "",
        "event": [
            "靈萌商店正式成立"
        ]
    },
    {
        "id": "3c",
        "name": "正式改組並成立靈萌團隊",
        "closed": true,
        "date": "2021/07/15",
        "description": "",
        "event": [
            "靈萌團隊成立",
            "經過團內選舉夏特稀當選團長",
            "萌弟(CuteUSB)當選副團長"
        ]
    },
    {
        "id": "2b",
        "name": "擬定新團隊",
        "closed": true,
        "date": "2021/07/12",
        "description": "",
        "event": [
            "舊團隊投票後解散並擬定新團隊"
        ]
    },
    {
        "id": "1a",
        "name": "發生事情",
        "closed": true,
        "date": "2014/03/15",
        "description": "簡短描述",
        "event": [
            "團隊成立"
        ]
    }
]